[{"id":2,"title":"2024年云计算行业发展趋势分析","author":"李华","category":"trend","summary":"云计算作为数字化转型的重要基础设施，在2024年将继续保持快速发展。本文分析了云计算行业的主要发展趋势和机遇。","content":"<h2>2024年云计算行业发展趋势分析</h2><p>云计算作为数字化转型的重要基础设施，在2024年将继续保持快速发展。本文分析了云计算行业的主要发展趋势和机遇。</p><p>首先，混合云将成为主流部署模式。企业既需要公有云的灵活性和成本优势，也需要私有云的安全性和可控性，混合云能够很好地满足这些需求。</p><p>其次，边缘计算将得到广泛应用。随着物联网设备的普及，边缘计算可以降低延迟，提高数据处理效率。</p><p>最后，云原生技术将更加成熟。容器化、微服务架构等云原生技术将帮助企业更好地利用云计算的优势。</p>","coverImage":"/uploads/covers/9076a350-730c-4071-9bc1-400285780a52.jpg","publishDate":"2024-01-10T14:30:00","createTime":"2024-01-10T14:30:00","updateTime":"2024-01-10T14:30:00","status":1,"viewCount":89},{"id":3,"title":"国家数据安全法实施要点解读","author":"王律师","category":"policy","summary":"《数据安全法》的实施对企业数据管理提出了新的要求。本文详细解读了法律要点和企业的合规建议。","content":"<h2>国家数据安全法实施要点解读</h2><p>《数据安全法》的实施对企业数据管理提出了新的要求。本文详细解读了法律要点和企业的合规建议。</p><p>法律明确了数据分类分级保护制度，企业需要根据数据的重要程度采取相应的保护措施。对于重要数据，企业需要建立专门的安全管理制度。</p><p>同时，法律要求企业建立数据安全风险评估机制，定期评估数据安全风险，及时发现和处置安全事件。</p><p>企业还需要建立数据安全事件应急预案，确保在发生安全事件时能够及时响应和处理。</p>","coverImage":"/uploads/covers/952415be-0626-4679-ae48-8d9918b2c6a7.jpg","publishDate":"2024-01-05T09:15:00","createTime":"2024-01-05T09:15:00","updateTime":"2024-01-05T09:15:00","status":1,"viewCount":234},{"id":4,"title":"腾讯云发布新一代企业级数据库产品","author":"陈记者","category":"company","summary":"腾讯云今日发布了新一代企业级数据库产品，该产品在性能、安全性和易用性方面都有显著提升。","content":"<h2>腾讯云发布新一代企业级数据库产品</h2><p>腾讯云今日发布了新一代企业级数据库产品，该产品在性能、安全性和易用性方面都有显著提升。</p><p>新产品采用了最新的分布式架构，支持水平扩展，可以满足大规模数据处理需求。同时，产品内置了多种安全机制，包括数据加密、访问控制等，确保数据安全。</p><p>在易用性方面，新产品提供了可视化的管理界面，降低了数据库管理的复杂度。此外，产品还支持多种编程语言的SDK，方便开发者集成。</p><p>腾讯云表示，该产品将帮助企业更好地应对数字化转型的挑战，提升业务效率。</p>","coverImage":"/uploads/covers/93c3d18b-ca9e-4282-a9d9-f2e261bc4611.jpg","publishDate":"2024-01-12T16:45:00","createTime":"2024-01-12T16:45:00","updateTime":"2024-01-12T16:45:00","status":1,"viewCount":67},{"id":5,"title":"Test News","author":"author","category":"tech","summary":"new summary","content":"content","coverImage":null,"publishDate":"2025-07-12T23:05:44","createTime":"2025-07-12T23:05:44","updateTime":"2025-07-12T23:05:44","status":1,"viewCount":0},{"id":6,"title":"Test News","author":"author","category":"tech","summary":"summary","content":"content","coverImage":null,"publishDate":"2025-07-12T23:05:44","createTime":"2025-07-12T23:05:44","updateTime":"2025-07-12T23:05:44","status":1,"viewCount":0},{"id":7,"title":"Test News","author":"author","category":"tech","summary":"new summary","content":"content","coverImage":null,"publishDate":"2025-07-12T23:10:03","createTime":"2025-07-12T23:10:03","updateTime":"2025-07-12T23:10:03","status":1,"viewCount":0},{"id":8,"title":"Test News","author":"author","category":"tech","summary":"summary","content":"content","coverImage":null,"publishDate":"2025-07-12T23:10:03","createTime":"2025-07-12T23:10:03","updateTime":"2025-07-12T23:10:03","status":1,"viewCount":0},{"id":9,"title":"Test News","author":"author","category":"tech","summary":"new summary","content":"content","coverImage":null,"publishDate":"2025-07-12T23:12:42","createTime":"2025-07-12T23:12:42","updateTime":"2025-07-12T23:12:42","status":1,"viewCount":0},{"id":10,"title":"Test News","author":"author","category":"tech","summary":"summary","content":"content","coverImage":null,"publishDate":"2025-07-12T23:12:42","createTime":"2025-07-12T23:12:42","updateTime":"2025-07-12T23:12:42","status":1,"viewCount":0},{"id":11,"title":"Test News","author":"author","category":"tech","summary":"new summary","content":"content","coverImage":null,"publishDate":"2025-07-12T23:15:53","createTime":"2025-07-12T23:15:53","updateTime":"2025-07-12T23:15:53","status":1,"viewCount":0},{"id":12,"title":"Test News","author":"author","category":"tech","summary":"summary","content":"content","coverImage":null,"publishDate":"2025-07-12T23:15:53","createTime":"2025-07-12T23:15:53","updateTime":"2025-07-12T23:15:53","status":1,"viewCount":0},{"id":13,"title":"Test News","author":"author","category":"tech","summary":"new summary","content":"content","coverImage":null,"publishDate":"2025-07-12T23:17:51","createTime":"2025-07-12T23:17:51","updateTime":"2025-07-12T23:17:51","status":1,"viewCount":0},{"id":14,"title":"Test News","author":"author","category":"tech","summary":"summary","content":"content","coverImage":null,"publishDate":"2025-07-12T23:17:51","createTime":"2025-07-12T23:17:51","updateTime":"2025-07-12T23:17:51","status":1,"viewCount":0},{"id":15,"title":"Test News","author":"author","category":"tech","summary":"new summary","content":"content","coverImage":null,"publishDate":"2025-07-12T23:22:45","createTime":"2025-07-12T23:22:45","updateTime":"2025-07-12T23:22:45","status":1,"viewCount":0},{"id":16,"title":"Test News","author":"author","category":"tech","summary":"summary","content":"content","coverImage":null,"publishDate":"2025-07-12T23:22:45","createTime":"2025-07-12T23:22:45","updateTime":"2025-07-12T23:22:45","status":1,"viewCount":0},{"id":17,"title":"Test News","author":"author","category":"tech","summary":"new summary","content":"content","coverImage":null,"publishDate":"2025-07-12T23:24:49","createTime":"2025-07-12T23:24:49","updateTime":"2025-07-12T23:24:49","status":1,"viewCount":0},{"id":18,"title":"Test News","author":"author","category":"tech","summary":"summary","content":"content","coverImage":null,"publishDate":"2025-07-12T23:24:49","createTime":"2025-07-12T23:24:49","updateTime":"2025-07-12T23:24:49","status":1,"viewCount":0},{"id":19,"title":"Test News","author":"author","category":"tech","summary":"new summary","content":"content","coverImage":null,"publishDate":"2025-07-12T23:28:21","createTime":"2025-07-12T23:28:21","updateTime":"2025-07-12T23:28:21","status":1,"viewCount":0},{"id":20,"title":"Test News","author":"author","category":"tech","summary":"summary","content":"content","coverImage":null,"publishDate":"2025-07-12T23:28:21","createTime":"2025-07-12T23:28:21","updateTime":"2025-07-12T23:28:21","status":1,"viewCount":0},{"id":21,"title":"t","author":"a","category":"c","summary":"s","content":"c","coverImage":null,"publishDate":"2025-07-12T23:32:15","createTime":"2025-07-12T23:32:15","updateTime":"2025-07-12T23:32:15","status":1,"viewCount":0},{"id":22,"title":"Test News","author":"author","category":"tech","summary":"new summary","content":"content","coverImage":null,"publishDate":"2025-07-12T23:32:15","createTime":"2025-07-12T23:32:15","updateTime":"2025-07-12T23:32:15","status":1,"viewCount":0},{"id":23,"title":"Test News","author":"author","category":"tech","summary":"summary","content":"content","coverImage":null,"publishDate":"2025-07-12T23:32:15","createTime":"2025-07-12T23:32:15","updateTime":"2025-07-12T23:32:15","status":1,"viewCount":0},{"id":24,"title":"t","author":"a","category":"c","summary":"s","content":"c","coverImage":null,"publishDate":"2025-07-12T23:34:28","createTime":"2025-07-12T23:34:28","updateTime":"2025-07-12T23:34:28","status":1,"viewCount":0},{"id":25,"title":"Test News","author":"author","category":"tech","summary":"new summary","content":"content","coverImage":null,"publishDate":"2025-07-12T23:34:28","createTime":"2025-07-12T23:34:28","updateTime":"2025-07-12T23:34:28","status":1,"viewCount":0},{"id":26,"title":"Test News","author":"author","category":"tech","summary":"summary","content":"content","coverImage":null,"publishDate":"2025-07-12T23:34:28","createTime":"2025-07-12T23:34:28","updateTime":"2025-07-12T23:34:28","status":1,"viewCount":0},{"id":27,"title":"t","author":"a","category":"c","summary":"s","content":"c","coverImage":null,"publishDate":"2025-07-12T23:35:41","createTime":"2025-07-12T23:35:41","updateTime":"2025-07-12T23:35:41","status":1,"viewCount":0},{"id":28,"title":"Test News","author":"author","category":"tech","summary":"new summary","content":"content","coverImage":null,"publishDate":"2025-07-12T23:35:41","createTime":"2025-07-12T23:35:41","updateTime":"2025-07-12T23:35:41","status":1,"viewCount":0},{"id":29,"title":"Test News","author":"author","category":"tech","summary":"summary","content":"content","coverImage":null,"publishDate":"2025-07-12T23:35:41","createTime":"2025-07-12T23:35:41","updateTime":"2025-07-12T23:35:41","status":1,"viewCount":0},{"id":30,"title":"t","author":"a","category":"c","summary":"s","content":"c","coverImage":null,"publishDate":"2025-07-12T23:43:46","createTime":"2025-07-12T23:43:46","updateTime":"2025-07-12T23:43:46","status":1,"viewCount":0},{"id":31,"title":"Test News","author":"author","category":"tech","summary":"new summary","content":"content","coverImage":null,"publishDate":"2025-07-12T23:43:46","createTime":"2025-07-12T23:43:46","updateTime":"2025-07-12T23:43:46","status":1,"viewCount":0},{"id":32,"title":"Test News","author":"author","category":"tech","summary":"summary","content":"content","coverImage":null,"publishDate":"2025-07-12T23:43:46","createTime":"2025-07-12T23:43:46","updateTime":"2025-07-12T23:43:46","status":1,"viewCount":0},{"id":33,"title":"t","author":"a","category":"c","summary":"s","content":"c","coverImage":null,"publishDate":"2025-07-12T23:45:06","createTime":"2025-07-12T23:45:06","updateTime":"2025-07-12T23:45:06","status":1,"viewCount":0},{"id":34,"title":"Test News","author":"author","category":"tech","summary":"new summary","content":"content","coverImage":null,"publishDate":"2025-07-12T23:45:06","createTime":"2025-07-12T23:45:06","updateTime":"2025-07-12T23:45:06","status":1,"viewCount":0},{"id":35,"title":"Test News","author":"author","category":"tech","summary":"summary","content":"content","coverImage":null,"publishDate":"2025-07-12T23:45:06","createTime":"2025-07-12T23:45:06","updateTime":"2025-07-12T23:45:06","status":1,"viewCount":0},{"id":36,"title":"t","author":"a","category":"c","summary":"s","content":"c","coverImage":null,"publishDate":"2025-07-13T00:16:36","createTime":"2025-07-13T00:16:36","updateTime":"2025-07-13T00:16:36","status":1,"viewCount":0},{"id":37,"title":"Test News","author":"author","category":"tech","summary":"new summary","content":"content","coverImage":null,"publishDate":"2025-07-13T00:16:36","createTime":"2025-07-13T00:16:36","updateTime":"2025-07-13T00:16:36","status":1,"viewCount":0},{"id":38,"title":"Test News","author":"author","category":"tech","summary":"summary","content":"content","coverImage":null,"publishDate":"2025-07-13T00:16:36","createTime":"2025-07-13T00:16:36","updateTime":"2025-07-13T00:16:36","status":1,"viewCount":0},{"id":39,"title":"t","author":"a","category":"c","summary":"s","content":"c","coverImage":null,"publishDate":"2025-07-13T00:21:52","createTime":"2025-07-13T00:21:52","updateTime":"2025-07-13T00:21:52","status":1,"viewCount":0},{"id":40,"title":"Test News","author":"author","category":"tech","summary":"new summary","content":"content","coverImage":null,"publishDate":"2025-07-13T00:21:52","createTime":"2025-07-13T00:21:52","updateTime":"2025-07-13T00:21:52","status":1,"viewCount":0},{"id":41,"title":"Test News","author":"author","category":"tech","summary":"summary","content":"content","coverImage":null,"publishDate":"2025-07-13T00:21:52","createTime":"2025-07-13T00:21:52","updateTime":"2025-07-13T00:21:52","status":1,"viewCount":0},{"id":42,"title":"t","author":"a","category":"c","summary":"s","content":"c","coverImage":null,"publishDate":"2025-07-13T00:23:55","createTime":"2025-07-13T00:23:55","updateTime":"2025-07-13T00:23:55","status":1,"viewCount":0},{"id":43,"title":"Test News","author":"author","category":"tech","summary":"new summary","content":"content","coverImage":null,"publishDate":"2025-07-13T00:23:55","createTime":"2025-07-13T00:23:55","updateTime":"2025-07-13T00:23:55","status":1,"viewCount":0},{"id":44,"title":"Test News","author":"author","category":"tech","summary":"summary","content":"content","coverImage":null,"publishDate":"2025-07-13T00:23:55","createTime":"2025-07-13T00:23:55","updateTime":"2025-07-13T00:23:55","status":1,"viewCount":0},{"id":45,"title":"t","author":"a","category":"c","summary":"s","content":"c","coverImage":null,"publishDate":"2025-07-13T00:25:50","createTime":"2025-07-13T00:25:50","updateTime":"2025-07-13T00:25:50","status":1,"viewCount":0},{"id":46,"title":"Test News","author":"author","category":"tech","summary":"new summary","content":"content","coverImage":null,"publishDate":"2025-07-13T00:25:50","createTime":"2025-07-13T00:25:50","updateTime":"2025-07-13T00:25:50","status":1,"viewCount":0},{"id":47,"title":"Test News","author":"author","category":"tech","summary":"summary","content":"content","coverImage":null,"publishDate":"2025-07-13T00:25:50","createTime":"2025-07-13T00:25:50","updateTime":"2025-07-13T00:25:50","status":1,"viewCount":0},{"id":48,"title":"t","author":"a","category":"c","summary":"s","content":"c","coverImage":null,"publishDate":"2025-07-13T00:26:59","createTime":"2025-07-13T00:26:59","updateTime":"2025-07-13T00:26:59","status":1,"viewCount":0},{"id":49,"title":"Test News","author":"author","category":"tech","summary":"new summary","content":"content","coverImage":null,"publishDate":"2025-07-13T00:26:59","createTime":"2025-07-13T00:26:59","updateTime":"2025-07-13T00:26:59","status":1,"viewCount":0},{"id":50,"title":"Test News","author":"author","category":"tech","summary":"summary","content":"content","coverImage":null,"publishDate":"2025-07-13T00:26:59","createTime":"2025-07-13T00:26:59","updateTime":"2025-07-13T00:26:59","status":1,"viewCount":0},{"id":51,"title":"t","author":"a","category":"c","summary":"s","content":"c","coverImage":null,"publishDate":"2025-07-13T00:31:19","createTime":"2025-07-13T00:31:19","updateTime":"2025-07-13T00:31:19","status":1,"viewCount":0},{"id":52,"title":"Test News","author":"author","category":"tech","summary":"new summary","content":"content","coverImage":null,"publishDate":"2025-07-13T00:31:19","createTime":"2025-07-13T00:31:19","updateTime":"2025-07-13T00:31:19","status":1,"viewCount":0},{"id":53,"title":"Test News","author":"author","category":"tech","summary":"summary","content":"content","coverImage":null,"publishDate":"2025-07-13T00:31:19","createTime":"2025-07-13T00:31:19","updateTime":"2025-07-13T00:31:19","status":1,"viewCount":0},{"id":54,"title":"t","author":"a","category":"c","summary":"s","content":"c","coverImage":null,"publishDate":"2025-07-13T00:33:06","createTime":"2025-07-13T00:33:06","updateTime":"2025-07-13T00:33:06","status":1,"viewCount":0},{"id":55,"title":"Test News","author":"author","category":"tech","summary":"new summary","content":"content","coverImage":null,"publishDate":"2025-07-13T00:33:06","createTime":"2025-07-13T00:33:06","updateTime":"2025-07-13T00:33:06","status":1,"viewCount":0},{"id":56,"title":"Test News","author":"author","category":"tech","summary":"summary","content":"content","coverImage":null,"publishDate":"2025-07-13T00:33:06","createTime":"2025-07-13T00:33:06","updateTime":"2025-07-13T00:33:06","status":1,"viewCount":0},{"id":57,"title":"t","author":"a","category":"c","summary":"s","content":"c","coverImage":null,"publishDate":"2025-07-13T00:37:01","createTime":"2025-07-13T00:37:01","updateTime":"2025-07-13T00:37:01","status":1,"viewCount":0},{"id":58,"title":"Test News","author":"author","category":"tech","summary":"new summary","content":"content","coverImage":null,"publishDate":"2025-07-13T00:37:01","createTime":"2025-07-13T00:37:01","updateTime":"2025-07-13T00:37:01","status":1,"viewCount":0},{"id":59,"title":"Test News","author":"author","category":"tech","summary":"summary","content":"content","coverImage":null,"publishDate":"2025-07-13T00:37:01","createTime":"2025-07-13T00:37:01","updateTime":"2025-07-13T00:37:01","status":1,"viewCount":0},{"id":60,"title":"t","author":"a","category":"c","summary":"s","content":"c","coverImage":null,"publishDate":"2025-07-13T00:44:17","createTime":"2025-07-13T00:44:17","updateTime":"2025-07-13T00:44:17","status":1,"viewCount":0},{"id":61,"title":"Test News","author":"author","category":"tech","summary":"new summary","content":"content","coverImage":null,"publishDate":"2025-07-13T00:44:17","createTime":"2025-07-13T00:44:17","updateTime":"2025-07-13T00:44:17","status":1,"viewCount":0},{"id":62,"title":"Test News","author":"author","category":"tech","summary":"summary","content":"content","coverImage":null,"publishDate":"2025-07-13T00:44:17","createTime":"2025-07-13T00:44:17","updateTime":"2025-07-13T00:44:17","status":1,"viewCount":0},{"id":63,"title":"t","author":"a","category":"c","summary":"s","content":"c","coverImage":null,"publishDate":"2025-07-13T00:46:18","createTime":"2025-07-13T00:46:18","updateTime":"2025-07-13T00:46:18","status":1,"viewCount":0},{"id":64,"title":"Test News","author":"author","category":"tech","summary":"new summary","content":"content","coverImage":null,"publishDate":"2025-07-13T00:46:18","createTime":"2025-07-13T00:46:18","updateTime":"2025-07-13T00:46:18","status":1,"viewCount":0},{"id":65,"title":"Test News","author":"author","category":"tech","summary":"summary","content":"content","coverImage":null,"publishDate":"2025-07-13T00:46:18","createTime":"2025-07-13T00:46:18","updateTime":"2025-07-13T00:46:18","status":1,"viewCount":0},{"id":66,"title":"t","author":"a","category":"c","summary":"s","content":"c","coverImage":null,"publishDate":"2025-07-13T00:47:04","createTime":"2025-07-13T00:47:04","updateTime":"2025-07-13T00:47:04","status":1,"viewCount":0},{"id":67,"title":"Test News","author":"author","category":"tech","summary":"new summary","content":"content","coverImage":null,"publishDate":"2025-07-13T00:47:04","createTime":"2025-07-13T00:47:04","updateTime":"2025-07-13T00:47:04","status":1,"viewCount":0},{"id":68,"title":"Test News","author":"author","category":"tech","summary":"summary","content":"content","coverImage":null,"publishDate":"2025-07-13T00:47:04","createTime":"2025-07-13T00:47:04","updateTime":"2025-07-13T00:47:04","status":1,"viewCount":0},{"id":69,"title":"t","author":"a","category":"c","summary":"s","content":"c","coverImage":null,"publishDate":"2025-07-13T00:50:46","createTime":"2025-07-13T00:50:46","updateTime":"2025-07-13T00:50:46","status":1,"viewCount":0},{"id":70,"title":"Test News","author":"author","category":"tech","summary":"new summary","content":"content","coverImage":null,"publishDate":"2025-07-13T00:50:46","createTime":"2025-07-13T00:50:46","updateTime":"2025-07-13T00:50:46","status":1,"viewCount":0},{"id":71,"title":"Test News","author":"author","category":"tech","summary":"summary","content":"content","coverImage":null,"publishDate":"2025-07-13T00:50:46","createTime":"2025-07-13T00:50:46","updateTime":"2025-07-13T00:50:46","status":1,"viewCount":0}]